cjkradlib/__init__.py
cjkradlib/__main__.py
cjkradlib/_decompose.py
cjkradlib/core.py
cjkradlib/data/Unihan_Variants.txt
cjkradlib/data/__init__.py
cjkradlib/data/cjk-decomp.txt
cjkradlib/data/cjkvi_ids/__init__.py
cjkradlib/data/cjkvi_ids/ids.txt
cjkradlib/data/jp/__init__.py
cjkradlib/data/jp/grade.json
cjkradlib/data/zh/__init__.py
cjkradlib/data/zh/junda.tsv
cjkradlib/decompose.py
cjkradlib/frequency.py
cjkradlib/variant.py
cjkradlib-0.2.0.1.dist-info/entry_points.txt
cjkradlib-0.2.0.1.dist-info/LICENSE
cjkradlib-0.2.0.1.dist-info/WHEEL
cjkradlib-0.2.0.1.dist-info/METADATA
cjkradlib-0.2.0.1.dist-info/RECORD
