Metadata-Version: 2.1
Name: cjkradlib
Version: 0.2.0.1
Summary: Generate compositions, supercompositions and variants for a given Hanzi / Kanji
Home-page: https://github.com/patarapolw/cjkradlib
Author: Pacharapol Withayasakpunt
Author-email: patarapolw@gmail.com
Keywords: cjk,hanzi,kanji,kangxi radical
Requires-Python: >=3.5
Classifier: License :: OSI Approved :: MIT License
Classifier: Programming Language :: Python :: 3
Classifier: Programming Language :: Python :: 3.5
Classifier: Programming Language :: Python :: 3.6
Classifier: Programming Language :: Python :: 3.7
Requires-Dist: click (>=7.0,<8.0)
Requires-Dist: importlib_resources (>=1.0,<2.0)
Requires-Dist: regex (>2018)
Project-URL: Repository, https://github.com/patarapolw/cjkradlib
